count_normalize/__init__.py
count_normalize/merge_normalize_isoform_count_v1.py
count_normalize/merge_normalized_isoform_count_TPM.py
count_normalize-0.1.1.dist-info/LICENSE
count_normalize-0.1.1.dist-info/METADATA
count_normalize-0.1.1.dist-info/WHEEL
count_normalize-0.1.1.dist-info/entry_points.txt
count_normalize-0.1.1.dist-info/top_level.txt
count_normalize-0.1.1.dist-info/RECORD
