Metadata-Version: 2.1
Name: count_normalize
Version: 0.1.1
Summary: Tools for normalizing isoform counts
Home-page: https://github.com/QiangSu/GaussF
Author: Qiang Su
Author-email: qiang_su@hotmail.com
License: YourLicense
Classifier: Programming Language :: Python :: 3
Classifier: License :: OSI Approved :: MIT License
Classifier: Operating System :: OS Independent
Requires-Python: >=3.6
License-File: LICENSE
